noxopt/__init__.py
noxopt/_config.py
noxopt/_option.py
noxopt/_tagging.py
noxopt/noxopt.py
noxopt/py.typed
noxopt-0.0.9.dist-info/LICENSE
noxopt-0.0.9.dist-info/METADATA
noxopt-0.0.9.dist-info/WHEEL
noxopt-0.0.9.dist-info/top_level.txt
noxopt-0.0.9.dist-info/RECORD
