Metadata-Version: 2.1
Name: noxopt
Version: 0.0.9
Summary: Nox sessions with options
Author-email: Ryan Morshead <ryan.morshead@gmail.com>
License: BSD-3-Clause
Project-URL: Homepage, https://github.com/rmorshea/noxopt
Classifier: Framework :: Django
Classifier: Programming Language :: Python :: 3
Requires-Python: >=3.7
License-File: LICENSE
Requires-Dist: nox
Requires-Dist: typing-extensions ; python_version < "3.10"
Requires-Dist: importlib-metadata ; python_version < "3.8"
